<?xml version="1.0" encoding="utf-8"?>
<!-- example file containing base tags -->

<game>	
	<title>Radical Graphics</title>
	<founding-date>October 1, 2013</founding-date>
	<website>http://www.radicalgraphics.com/</website>
	<based-in>Amsterdam, The Netherlands</based-in>
	
	<press-contact>info@radicalgraphics.com</press-contact>
	<phone>+31 (0) 639201181</phone>
	<address>
		<line>Overhoeksplein, 2. A-Lab.101</line>
		<line>1031KS Amsterdam, The Netherlands</line>
	</address>

	<socials>
		<social>
			<name>twitter.com/radicalgraph1cs</name>
			<link>twitter.com/radicalgraph1cs</link>
		</social>
		<social>
			<name>facebook.com/radicalgraphics</name>
			<link>facebook.com/radicalgraphics</link>
		</social>
		<social>
			<name>Skype</name>
			<link>callto:radicalgraphics</link>
		</social>
	</socials>

	<description>	
		Radical Graphics is an Indie Development Studio based in Amsterdam, Europe that designs and develops entertainment software such as Web Apps, Games and Gamification solutions.
		The studio is made up of Manuel González and José Gómez de Lara, two game industry veterans going indie to the exciting future : Unity, Ouya, Mobile, Web Apps, Gamification &amp; Virtual Reality.
	</description>
		
	<histories>
		<history>
			<header>Early Prehistoric times</header>
			<text>It all started by three friends at the end of XXth Century in a borrowed office space in Costa del Sol, Southern Spain.Radical Graphics Studios was founded as a moniker for naming their different projects . They, as courious kids tried to tinker with a wide range of stuff: web, shortfilm production, game development, mobile research, video, music, fashion, social networks (yes in 1999!), etc... These collaborations lead them to study Software Engineering at university. (in Spain.What a bunch of lucky guys...) 			
			</text>
		</history>
		<history>
			<header>Early history</header>
			<text>We created the company in Amsterdam.</text>
		</history>
		<history>
			<header>After that</header>
			<text>We created the company in Amsterdam.</text>
		</history>
	</histories>
	
	<trailers>
		<trailer>
			<name>Radical Video in Progress
			</name>
			<youtube>sr2BcDSa2H8</youtube>
		</trailer>
	</trailers>
	
	<awards>
		<award>
			<description>Winner in this highly relevant contest.</description>
			<info>Award Location, 20 October, 1989</info>
		</award>
		<award>
			<description>Nomination for this prestigious award.</description>
			<info>Award Ceremony, 4 December, 1991</info>
		</award>
		<award>
			<description>Winner in this highly relevant contest.</description>
			<info>Award Location, 20 October, 1989</info>
		</award>
		<award>
			<description>Nomination for this prestigious award.</description>
			<info>Award Ceremony, 4 December, 1991</info>
		</award>
	</awards>
	
	<quotes>
		<quote>
			<description>This is a rather insignificant quote by a highly important person.</description>
			<name>Person Name</name>
			<website>Website</website>
			<link>http://www.website.com/</link>
		</quote>
		<quote>
			<description>An extremely positive quote from a rather insignificant person. Also great.</description>
			<name>Some Guy</name>
			<website>This Page Is Visited By 12 Visitors A Month</website>
			<link>http://geocities.blog.com/</link>
		</quote>
		<quote>
			<description>I pretend to love this game even though I do not actually understand it.</description>
			<name>Pretentious Bastard</name>
			<website>Artsy Page</website>
			<link>http://art.tumblr.com/</link>
		</quote>
		<quote>
			<description>HOLY SHIT SO AMAZING</description>
			<name>Caps Guy</name>
			<website>Angry Review</website>
			<link>http://thispage.net/angrytube</link>
		</quote>
	</quotes>
	
	<press-can-request-copy>TRUE</press-can-request-copy> <!-- can be true or false -->
	<monetization-permission>monetize</monetization-permission> <!-- can be: 	false (no video allowed),
																			 	ask (permission on case-per-case basis),
																			 	non-commercial (no monetization allowed),
																			 	monetize (full permission) -->	
	<additionals>
		<additional>
			<title>Company Link #1</title>
			<description>This link is a link that might be useful. You can check it out at</description>
			<link>http://somemusicsite.com/thislink</link>
		</additional>
	</additionals>
	
	<credits>
		<credit>
			<person>Manuel González</person>
			<website>www.twitter.com/leunamsan</website>
			<role>Cofounder - Creative Director, Radical Graphics Studios</role>
		</credit>
		<credit>
			<person>José Gómez de Lara</person>
			<website>www.twitter.com/bochelord</website>
			<role>Cofounder - CTO, Radical Graphics Studios</role>
		</credit>
		<credit>
			<person>William Perry</person>
			<website>http://nl.linkedin.com/in/williameperry/en</website>
			<role>Junior Developer, Radical Graphics Studios</role>
		</credit>

		<credit>
			<person>Andrés Martínez</person>
			<website>http://nl.linkedin.com/in/williameperry/en</website>
			<role>Lead Artist, DoubleRing Studios</role>
		</credit>
	</credits>
	
	<contacts>
		<contact>
			<name>Inquiries</name>
			<mail>info@radicalgraphics.com</mail>
		</contact>
		<contact>
			<name>Twitter</name>
			<link>http://twitter.com/radicalgraph1cs</link>
		</contact>
		<contact>
			<name>Facebook</name>
			<link>http://facebook.com/radicalgraphics</link>
		</contact>
		<contact>
			<name>Web</name>
			<link>radicalgraphics.com</link>
		</contact>
	</contacts>
</game>